<PAMDataset>
  <Metadata>
    <MDI key="DataType">Generic</MDI>
  </Metadata>
  <Metadata domain="Esri">
    <MDI key="PyramidResamplingType">NEAREST</MDI>
  </Metadata>
  <PAMRasterBand band="1">
    <Description>Band_1</Description>
    <Histograms>
      <HistItem>
        <HistMin>784.2169189453125</HistMin>
        <HistMax>801.093994140625</HistMax>
        <BucketCount>256</BucketCount>
        <IncludeOutOfRange>1</IncludeOutOfRange>
        <Approximate>0</Approximate>
        <HistCounts>10|40|116|225|343|428|507|519|620|776|949|1184|1266|1235|1396|1687|2126|2129|2128|1876|2102|2402|2410|2634|3201|4385|5566|4720|4295|4386|4377|3989|4124|4433|4807|4714|4359|4380|4676|4746|4530|4896|5411|5497|5806|6255|6919|7127|6786|6759|6388|6566|6902|7034|7072|6688|6645|6519|6622|6668|6478|6209|6245|6415|6728|6813|6978|6980|7239|7121|7602|8000|8129|8280|8093|7738|7922|7765|7905|7371|6412|5464|5188|4936|5199|4777|4648|4164|3515|3098|3181|3244|3673|3920|4095|4191|4414|4586|4974|5161|4283|3961|3586|3508|3294|3199|3643|3638|3449|3430|3101|2526|2376|1991|1755|1859|1840|1836|1997|1995|1694|1627|1462|1520|1570|1731|1725|1635|1863|1838|1887|1718|1621|1502|1445|1656|1734|1611|1759|1665|1429|1246|997|623|315|166|137|116|95|72|67|55|55|49|47|45|39|46|36|39|37|35|38|36|40|32|35|37|33|35|39|35|32|33|36|34|26|37|27|32|24|35|25|25|29|24|26|27|31|25|30|25|28|26|34|22|30|29|24|30|30|31|31|25|32|20|36|24|32|29|26|33|26|37|29|30|28|40|31|37|36|44|23|44|42|42|37|39|43|35|42|42|38|41|36|37|42|44|37|50|49|53|49|58|60|56|72|63|101|136|169|190|252|123|18|1</HistCounts>
      </HistItem>
    </Histograms>
    <Metadata>
      <MDI key="BandName">Band_1</MDI>
      <MDI key="RepresentationType">ATHEMATIC</MDI>
      <MDI key="STATISTICS_COVARIANCES">4.777491408823235</MDI>
      <MDI key="STATISTICS_EXCLUDEDVALUES"></MDI>
      <MDI key="STATISTICS_MAXIMUM">801.09399414063</MDI>
      <MDI key="STATISTICS_MEAN">788.88490938921</MDI>
      <MDI key="STATISTICS_MINIMUM">784.21691894531</MDI>
      <MDI key="STATISTICS_SKIPFACTORX">1</MDI>
      <MDI key="STATISTICS_SKIPFACTORY">1</MDI>
      <MDI key="STATISTICS_STDDEV">2.1857473341682</MDI>
    </Metadata>
  </PAMRasterBand>
</PAMDataset>
