<PAMDataset>
  <Metadata>
    <MDI key="DataType">Generic</MDI>
  </Metadata>
  <Metadata domain="Esri">
    <MDI key="PyramidResamplingType">NEAREST</MDI>
  </Metadata>
  <PAMRasterBand band="1">
    <Description>Band_1</Description>
    <Histograms>
      <HistItem>
        <HistMin>806.885009765625</HistMin>
        <HistMax>868.1810302734375</HistMax>
        <BucketCount>256</BucketCount>
        <IncludeOutOfRange>1</IncludeOutOfRange>
        <Approximate>0</Approximate>
        <HistCounts>109|850|1031|449|353|620|665|766|911|967|1367|1514|1343|1601|1272|1021|1084|967|793|750|793|721|693|661|665|647|648|629|628|629|595|653|685|686|620|616|639|652|561|563|559|522|642|518|525|543|569|730|513|458|408|414|414|407|363|388|365|358|378|383|603|804|1134|1513|1775|2257|2382|2676|3187|3167|3242|3540|3538|4059|4026|3368|3275|3049|2914|2971|2898|2762|2727|2682|2584|2682|2642|2654|2708|2668|2761|2658|2680|2782|2687|2805|2863|2972|2940|3211|3277|3103|2923|2928|3055|3045|3082|3128|3044|3034|3024|3087|3110|3307|3189|3057|3244|3288|3230|3353|3470|3451|3561|3597|3434|3374|3673|3601|3579|3528|3723|3605|3578|3603|3628|3546|3897|3396|3376|3541|3520|3468|3268|3464|3249|3350|3304|3432|3465|4091|4047|3798|3833|3970|4059|4106|4250|4412|4606|4540|4086|3790|3763|3354|3283|3258|3248|3372|3210|3394|3725|4153|4585|5194|4666|4343|4490|4963|5487|4511|4140|3919|3487|2948|2754|2712|2496|2504|2628|2262|2228|2177|2114|2001|2127|2211|2260|2194|2067|2013|2020|1966|2038|2172|2021|1970|1963|1947|1943|1920|2091|1934|1944|2057|1869|2022|1687|1510|1369|1290|1270|1196|1227|1313|1488|1514|1447|1469|1431|1507|1492|1509|1402|1423|1422|1421|1387|1208|968|929|948|833|829|702|609|579|528|419|193|102|64|56|59|56|28|1</HistCounts>
      </HistItem>
    </Histograms>
    <Metadata>
      <MDI key="BandName">Band_1</MDI>
      <MDI key="RepresentationType">ATHEMATIC</MDI>
      <MDI key="STATISTICS_COVARIANCES">171.9254747269026</MDI>
      <MDI key="STATISTICS_EXCLUDEDVALUES"></MDI>
      <MDI key="STATISTICS_MAXIMUM">868.18103027344</MDI>
      <MDI key="STATISTICS_MEAN">839.60318779664</MDI>
      <MDI key="STATISTICS_MINIMUM">806.88500976563</MDI>
      <MDI key="STATISTICS_SKIPFACTORX">1</MDI>
      <MDI key="STATISTICS_SKIPFACTORY">1</MDI>
      <MDI key="STATISTICS_STDDEV">13.112035491368</MDI>
    </Metadata>
  </PAMRasterBand>
</PAMDataset>
