<PAMDataset>
  <Metadata>
    <MDI key="DataType">Generic</MDI>
  </Metadata>
  <Metadata domain="Esri">
    <MDI key="PyramidResamplingType">NEAREST</MDI>
  </Metadata>
  <PAMRasterBand band="1">
    <Description>Band_1</Description>
    <Histograms>
      <HistItem>
        <HistMin>928.4239501953125</HistMin>
        <HistMax>951.6569213867188</HistMax>
        <BucketCount>256</BucketCount>
        <IncludeOutOfRange>1</IncludeOutOfRange>
        <Approximate>0</Approximate>
        <HistCounts>7|15|18|17|18|16|20|24|23|28|32|22|32|43|30|51|52|55|34|51|48|48|48|56|61|70|72|108|131|158|227|242|274|293|281|292|334|315|350|371|408|406|385|393|409|464|515|489|476|522|498|572|512|515|593|644|685|779|871|717|732|713|703|714|732|722|728|734|731|739|789|778|853|866|932|937|970|938|973|968|955|1017|1040|1039|1046|1051|1151|1115|1160|1140|1200|1181|1155|1206|1203|1221|1223|1285|1292|1261|1314|1277|1297|1294|1349|1378|1307|1407|1333|1435|1429|1445|1470|1520|1576|1570|1612|1591|1610|1736|1694|1767|1701|1829|1792|1856|1876|1885|1996|1960|1985|2100|2067|2069|2064|2030|2061|2115|2137|2161|2284|2182|2276|2394|2397|2476|2544|2547|2467|2646|2748|2714|2753|2698|2777|2760|3134|3215|3262|3051|3229|3405|3525|3587|3717|4090|4398|4701|5390|6355|6912|7805|7165|7118|7227|7010|6681|7119|7393|7126|7084|7410|8162|8426|8504|8744|8299|7770|7596|7532|7909|7597|7717|7568|7159|7274|6516|5942|6085|6211|6245|6159|5594|4915|4426|4893|4758|4736|3973|3837|3620|3576|3385|3266|3573|3560|3404|3251|3010|2298|2377|2286|1905|1795|1870|1703|1499|1432|1350|1472|1549|1726|1729|1639|1471|1160|1010|1012|932|882|858|760|915|847|838|759|1001|1216|1012|650|497|393|155|20|9|1</HistCounts>
      </HistItem>
    </Histograms>
    <Metadata>
      <MDI key="BandName">Band_1</MDI>
      <MDI key="RepresentationType">ATHEMATIC</MDI>
      <MDI key="STATISTICS_COVARIANCES">16.05040538166023</MDI>
      <MDI key="STATISTICS_EXCLUDEDVALUES"></MDI>
      <MDI key="STATISTICS_MAXIMUM">951.65692138672</MDI>
      <MDI key="STATISTICS_MEAN">943.78285123947</MDI>
      <MDI key="STATISTICS_MINIMUM">928.42395019531</MDI>
      <MDI key="STATISTICS_SKIPFACTORX">1</MDI>
      <MDI key="STATISTICS_SKIPFACTORY">1</MDI>
      <MDI key="STATISTICS_STDDEV">4.0062957181991</MDI>
    </Metadata>
  </PAMRasterBand>
</PAMDataset>
