<PAMDataset>
  <Metadata>
    <MDI key="DataType">Generic</MDI>
  </Metadata>
  <Metadata domain="Esri">
    <MDI key="PyramidResamplingType">NEAREST</MDI>
  </Metadata>
  <PAMRasterBand band="1">
    <Description>Band_1</Description>
    <Histograms>
      <HistItem>
        <HistMin>852.8900146484375</HistMin>
        <HistMax>915.85693359375</HistMax>
        <BucketCount>256</BucketCount>
        <IncludeOutOfRange>1</IncludeOutOfRange>
        <Approximate>0</Approximate>
        <HistCounts>39|122|197|200|223|224|243|244|249|298|349|208|203|204|202|206|206|213|253|282|307|320|283|274|285|272|304|282|292|317|308|320|332|320|324|348|315|349|333|348|339|368|404|381|349|374|400|421|471|550|739|968|1362|1699|1819|2019|1908|1993|1966|1834|1747|1755|1727|1791|1830|1979|1945|1912|1862|1893|1944|2032|2032|2025|2051|1976|2097|2092|2123|2250|2153|2133|2086|2226|2149|2232|2362|2367|2451|2246|2167|2086|2105|2147|2224|2345|2512|2565|2454|2445|2423|2510|2604|2741|2815|2787|2678|2694|2608|2613|2660|2827|2709|2526|2507|2408|2585|2912|2805|2859|3001|2975|2982|2925|2920|2429|1924|1886|2052|2509|3287|3627|3632|3639|3208|3281|3094|2830|2814|2868|2892|2656|2225|2010|1914|2354|2727|2920|2972|3014|3368|3759|4027|4420|4249|4472|4825|4592|4112|3999|4342|4316|4275|4538|4284|4192|4249|4052|3782|3331|3231|3247|3511|3769|3463|3426|3364|5975|8768|7459|5470|6544|4087|1920|1839|1842|1652|1513|1376|1197|1337|1174|1185|1171|1169|1212|1200|1231|1254|1234|1151|1184|1323|1318|1334|1803|2918|3540|2814|2358|2528|3216|3995|4705|5068|5158|4716|3282|3136|2641|2030|2399|2587|2183|2335|1796|1680|1411|1154|1143|1215|1341|1242|1175|1143|1016|884|1022|1103|1136|1101|1157|1250|1254|1252|1347|1717|1911|7738|8600|17168|8016|322|40|121|1</HistCounts>
      </HistItem>
    </Histograms>
    <Metadata>
      <MDI key="BandName">Band_1</MDI>
      <MDI key="RepresentationType">ATHEMATIC</MDI>
      <MDI key="STATISTICS_COVARIANCES">206.7324438330197</MDI>
      <MDI key="STATISTICS_EXCLUDEDVALUES"></MDI>
      <MDI key="STATISTICS_MAXIMUM">915.85693359375</MDI>
      <MDI key="STATISTICS_MEAN">890.87266655893</MDI>
      <MDI key="STATISTICS_MINIMUM">852.89001464844</MDI>
      <MDI key="STATISTICS_SKIPFACTORX">1</MDI>
      <MDI key="STATISTICS_SKIPFACTORY">1</MDI>
      <MDI key="STATISTICS_STDDEV">14.378193343846</MDI>
    </Metadata>
  </PAMRasterBand>
</PAMDataset>
