<PAMDataset>
  <Metadata>
    <MDI key="DataType">Generic</MDI>
  </Metadata>
  <Metadata domain="Esri">
    <MDI key="PyramidResamplingType">NEAREST</MDI>
  </Metadata>
  <PAMRasterBand band="1">
    <Description>Band_1</Description>
    <Histograms>
      <HistItem>
        <HistMin>800.9119873046875</HistMin>
        <HistMax>890.5360107421875</HistMax>
        <BucketCount>256</BucketCount>
        <IncludeOutOfRange>1</IncludeOutOfRange>
        <Approximate>0</Approximate>
        <HistCounts>1317|6114|21229|37603|33426|32031|34789|30411|25093|15772|8904|7987|9891|10233|8544|8218|6428|5808|5749|6275|6614|5598|5666|5310|5071|4333|4252|4099|3721|3380|3525|3336|3008|2785|2237|2013|1955|1823|1882|2036|1859|1833|1761|1831|1977|2113|1966|1955|2004|1983|1934|1773|1717|1627|1594|1604|1630|1546|1545|1597|1652|1710|1819|1712|1583|1621|1588|1731|1760|1920|2008|2176|1949|1904|1828|1685|1490|1969|1874|1659|1486|1385|1276|1297|1396|1381|1218|1073|1102|1046|1145|1214|1153|1161|1214|1218|1204|1226|1145|1271|1231|1280|1239|1317|1407|1338|1295|1369|1289|1218|1154|1116|1085|1137|1077|1151|1119|1013|1032|991|894|816|777|722|752|773|772|754|734|717|695|638|656|675|671|671|664|677|660|653|625|617|564|546|533|505|480|501|480|512|486|504|454|473|463|474|467|457|468|458|461|444|445|449|415|416|406|394|378|390|404|394|398|384|411|397|353|369|381|370|365|355|358|342|383|371|380|370|392|382|394|391|431|456|439|444|440|452|452|490|514|609|586|617|571|621|602|677|501|522|482|435|373|357|357|341|308|270|264|253|220|215|196|206|242|219|216|266|200|143|105|133|129|131|112|125|145|156|128|109|102|93|80|74|83|79|65|58|48|39|35|25|28|20|8|1</HistCounts>
      </HistItem>
    </Histograms>
    <Metadata>
      <MDI key="BandName">Band_1</MDI>
      <MDI key="RepresentationType">ATHEMATIC</MDI>
      <MDI key="STATISTICS_COVARIANCES">337.6633823224571</MDI>
      <MDI key="STATISTICS_EXCLUDEDVALUES"></MDI>
      <MDI key="STATISTICS_MAXIMUM">890.53601074219</MDI>
      <MDI key="STATISTICS_MEAN">815.14461656501</MDI>
      <MDI key="STATISTICS_MINIMUM">800.91198730469</MDI>
      <MDI key="STATISTICS_SKIPFACTORX">1</MDI>
      <MDI key="STATISTICS_SKIPFACTORY">1</MDI>
      <MDI key="STATISTICS_STDDEV">18.375619236435</MDI>
    </Metadata>
  </PAMRasterBand>
</PAMDataset>
